alpha3/__init__.py
alpha3/__main__.py
alpha3/get_alpha3.py
alpha3-0.1.3.dist-info/LICENSE
alpha3-0.1.3.dist-info/METADATA
alpha3-0.1.3.dist-info/WHEEL
alpha3-0.1.3.dist-info/entry_points.txt
alpha3-0.1.3.dist-info/RECORD
